fping/__init__.py
fping/backends/__init__.py
fping/backends/base.py
fping/backends/fping.py
fpingwrppr-0.7.dist-info/METADATA
fpingwrppr-0.7.dist-info/WHEEL
fpingwrppr-0.7.dist-info/top_level.txt
fpingwrppr-0.7.dist-info/zip-safe
fpingwrppr-0.7.dist-info/RECORD
