Metadata-Version: 2.1
Name: fpingwrppr
Version: 0.7
Summary: Fping Wrapper
Author: gabriel
License: MIT
Keywords: ping
